{
  "lastRunAt": "2026-07-17T18:30:06.217Z",
  "lastSuccessAt": "2026-07-17T18:30:06.217Z",
  "lastFetchAt": "2026-07-17T18:30:06.237Z",
  "lastParseAt": "2026-07-17T18:30:06.217Z",
  "lastError": null,
  "consecutiveFailures": 0,
  "lastSnapshotCount": 9,
  "lastHeartbeatLocalDate": "2026-07-17",
  "lastHeartbeatSentAt": "2026-07-17T06:05:02.232Z",
  "searchUrl": "https://udlejning.cej.dk/find-bolig/overblik?collection=residences&monthlyPrice=0-12000&p=sj%C3%A6lland%2Ck%C3%B8benhavn&types=apartment"
}
